tst/alu.sv
//`timescale 1ns / 1ps
//////////////////////////////////////////////////////////////////////////////////
// Company: 
// Engineer: 
// 
// Create Date: 09/26/2022 01:54:05 AM
// Design Name: 
// Module Name: alu_io
// Project Name: 
// Target Devices: 
// Tool Versions: 
// Description: 
// 
// Dependencies: 
// 
// Revision:
// Revision 0.01 - File Created
// Additional Comments:
// 
//////////////////////////////////////////////////////////////////////////////////

module alu
#(parameter XLEN=32) 
(
    input logic [XLEN-1:0] a,b,
    input logic [3:0] op,
    output logic [XLEN-1:0] r, 
    output logic z, v
);
    localparam SHLEN=$clog2(XLEN);
    logic signed [2*XLEN-1:0] p;
    logic signed [XLEN-1:0] s;
    assign s = $signed(a) + $signed(b);    
    assign p = $signed(a) * $signed(b);


    always @* //always_comb
        case (op)
            4'b0000: r= a&b;
            4'b0001: r= a|b;
            4'b0010: r= a+b; //s;
            4'b0011: r= p[XLEN-1:0];
            4'b0100: r= p[2*XLEN-1:XLEN];
            4'b0110: r= $signed(a)-$signed(b);
            4'b0111: r= ($signed(a)<$signed(b))?1:0;
            4'b1000: r= a>>b[SHLEN-1:0];
            4'b1001: r= a<<b[SHLEN-1:0];
            4'b1010: r= $signed(a)>>>b[SHLEN-1:0];
            4'b1100: r= ~(a|b);
            4'b1101: r= a^b;
            4'b1110: r= $signed(a) / $signed(b);            
            4'b1111: r= $signed(a) % $signed(b);                                                           
            default: r= 'X;
        endcase       
          
    assign z=~|r;
    //assign v = (a[XLEN-1]^b[XLEN-1]) ? 0: (r[XLEN-1]^a[XLEN-1]);
    assign v = (op==4'b0010 || op==4'b0110) ?
               ((a[XLEN-1]^b[XLEN-1]) ? 0: (r[XLEN-1]^a[XLEN-1])) : 1'b0;

endmodule

tst/alu1_tb.sv
`timescale 1ns / 1ns

module alu1_tb
#(  parameter XLEN=32)
();

  // Inputs
  logic clk, rst;
  logic [XLEN-1:0] a, b;
  logic [3:0] op;
  logic [XLEN-1:0] r; 
  logic z, v;
  int i, j,k;

  // Instantiate the Unit Under Test (UUT)
  alu
    #(XLEN)
    uut (a, b, op, r, z, v);

  // Clock generation
  localparam PERIOD = 8; // 125 MHz
  always
    begin
      clk = 1'b0;
      #(PERIOD/2) clk = 1'b1;
      #(PERIOD/2);
    end

  // Stimulus
  initial
    begin
      $dumpfile("alu1.vcd");
      $dumpvars(0,alu1_tb);
      //for (ii=1;ii<16;ii=ii+1) $dumpvars(0, rvx1_tb.uut.x[ii]);
      // Initialize Inputs
      clk = 0;
      rst = 1;
      #20 rst = 0;

      for (i=-4;i<4;i++) begin
        #1;
        for (j=4;j>-4;j--) begin
          #1;
          for (k=0;k<16;k++) begin
            @(posedge clk);
            a=i; b=j; op=k;
            @(negedge clk);
            $display("%t: %d op(%b) %d = %d (%b,%b)",$time,$signed(a),op,$signed(b),$signed(r),z,v);
            #1 i++;j--;
          end
        end
      end
      #200 $finish;//$stop;
    end
  
endmodule // alu1_tb

tst/build/alu1.vcd
$date
	Fri Jan 26 02:04:44 2024
$end
$version
	Icarus Verilog
$end
$timescale
	1ns
$end
$scope module alu1_tb $end
$var wire 1 ! z $end
$var wire 1 " v $end
$var wire 32 # r [31:0] $end
$var parameter 32 $ PERIOD $end
$var parameter 32 % XLEN $end
$var reg 32 & a [31:0] $end
$var reg 32 ' b [31:0] $end
$var reg 1 ( clk $end
$var reg 4 ) op [3:0] $end
$var reg 1 * rst $end
$var integer 32 + i [31:0] $end
$var integer 32 , j [31:0] $end
$var integer 32 - k [31:0] $end
$scope module uut $end
$var wire 32 . a [31:0] $end
$var wire 32 / b [31:0] $end
$var wire 4 0 op [3:0] $end
$var wire 1 ! z $end
$var wire 1 " v $end
$var wire 32 1 s [31:0] $end
$var wire 64 2 p [63:0] $end
$var parameter 32 3 SHLEN $end
$var parameter 32 4 XLEN $end
$var reg 32 5 r [31:0] $end
$upscope $end
$upscope $end
$enddefinitions $end
$comment Show the parameter values. $end
$dumpall
b100000 4
b101 3
b100000 %
b1000 $
$end
#0
$dumpvars
bx 5
bx 2
bx 1
bx 0
bx /
bx .
b0 -
b0 ,
b0 +
1*
bx )
0(
bx '
bx &
bx #
x"
x!
$end
#4
1(
#8
0(
#12
1(
#16
0(
#20
1(
b11111111111111111111111111111100 +
0*
#21
b100 ,
#24
0(
#28
0"
0!
b100 #
b100 5
b0 )
b0 0
b0 1
b1111111111111111111111111111111111111111111111111111111111110000 2
b100 '
b100 /
b11111111111111111111111111111100 &
b11111111111111111111111111111100 .
1(
#32
0(
#33
b1 -
b11 ,
b11111111111111111111111111111101 +
#36
b11111111111111111111111111111111 #
b11111111111111111111111111111111 5
b1 )
b1 0
b11 '
b11 /
b0 1
b1111111111111111111111111111111111111111111111111111111111110111 2
b11111111111111111111111111111101 &
b11111111111111111111111111111101 .
1(
#40
0(
#41
b10 -
b10 ,
b11111111111111111111111111111110 +
#44
1!
b0 #
b0 5
b10 )
b10 0
b10 '
b10 /
b0 1
b1111111111111111111111111111111111111111111111111111111111111100 2
b11111111111111111111111111111110 &
b11111111111111111111111111111110 .
1(
#48
0(
#49
b11 -
b1 ,
b11111111111111111111111111111111 +
#52
0!
b11111111111111111111111111111111 #
b11111111111111111111111111111111 5
b11 )
b11 0
b1 '
b1 /
b0 1
b1111111111111111111111111111111111111111111111111111111111111111 2
b11111111111111111111111111111111 &
b11111111111111111111111111111111 .
1(
#56
0(
#57
b100 -
b0 ,
b0 +
#60
1!
b0 #
b0 5
b100 )
b100 0
b0 '
b0 /
b0 1
b0 2
b0 &
b0 .
1(
#64
0(
#65
b101 -
b11111111111111111111111111111111 ,
b1 +
#68
x!
bx #
bx 5
b101 )
b101 0
b1111111111111111111111111111111111111111111111111111111111111111 2
b11111111111111111111111111111111 '
b11111111111111111111111111111111 /
b0 1
b1 &
b1 .
1(
#72
0(
#73
b110 -
b11111111111111111111111111111110 ,
b10 +
#76
0!
b100 #
b100 5
b110 )
b110 0
b11111111111111111111111111111110 '
b11111111111111111111111111111110 /
b0 1
b1111111111111111111111111111111111111111111111111111111111111100 2
b10 &
b10 .
1(
#80
0(
#81
b111 -
b11111111111111111111111111111101 ,
b11 +
#84
1!
b0 #
b0 5
b111 )
b111 0
b11111111111111111111111111111101 '
b11111111111111111111111111111101 /
b0 1
b1111111111111111111111111111111111111111111111111111111111110111 2
b11 &
b11 .
1(
#88
0(
#89
b1000 -
b11111111111111111111111111111100 ,
b100 +
#92
b1000 )
b1000 0
b11111111111111111111111111111100 '
b11111111111111111111111111111100 /
b0 1
b1111111111111111111111111111111111111111111111111111111111110000 2
b100 &
b100 .
1(
#96
0(
#97
b1001 -
b11111111111111111111111111111011 ,
b101 +
#100
0!
b101000000000000000000000000000 #
b101000000000000000000000000000 5
b1001 )
b1001 0
b11111111111111111111111111111011 '
b11111111111111111111111111111011 /
b0 1
b1111111111111111111111111111111111111111111111111111111111100111 2
b101 &
b101 .
1(
#104
0(
#105
b1010 -
b11111111111111111111111111111010 ,
b110 +
#108
1!
b0 #
b0 5
b1010 )
b1010 0
b11111111111111111111111111111010 '
b11111111111111111111111111111010 /
b0 1
b1111111111111111111111111111111111111111111111111111111111011100 2
b110 &
b110 .
1(
#112
0(
#113
b1011 -
b11111111111111111111111111111001 ,
b111 +
#116
x!
bx #
bx 5
b1011 )
b1011 0
b11111111111111111111111111111001 '
b11111111111111111111111111111001 /
b0 1
b1111111111111111111111111111111111111111111111111111111111001111 2
b111 &
b111 .
1(
#120
0(
#121
b1100 -
b11111111111111111111111111111000 ,
b1000 +
#124
0!
b111 #
b111 5
b1100 )
b1100 0
b11111111111111111111111111111000 '
b11111111111111111111111111111000 /
b0 1
b1111111111111111111111111111111111111111111111111111111111000000 2
b1000 &
b1000 .
1(
#128
0(
#129
b1101 -
b11111111111111111111111111110111 ,
b1001 +
#132
b11111111111111111111111111111110 #
b11111111111111111111111111111110 5
b1101 )
b1101 0
b11111111111111111111111111110111 '
b11111111111111111111111111110111 /
b0 1
b1111111111111111111111111111111111111111111111111111111110101111 2
b1001 &
b1001 .
1(
#136
0(
#137
b1110 -
b11111111111111111111111111110110 ,
b1010 +
#140
b11111111111111111111111111111111 #
b11111111111111111111111111111111 5
b1110 )
b1110 0
b11111111111111111111111111110110 '
b11111111111111111111111111110110 /
b0 1
b1111111111111111111111111111111111111111111111111111111110011100 2
b1010 &
b1010 .
1(
#144
0(
#145
b1111 -
b11111111111111111111111111110101 ,
b1011 +
#148
1!
b0 #
b0 5
b1111 )
b1111 0
b11111111111111111111111111110101 '
b11111111111111111111111111110101 /
b0 1
b1111111111111111111111111111111111111111111111111111111110000111 2
b1011 &
b1011 .
1(
#152
0(
#153
b10000 -
b11111111111111111111111111110011 ,
b1101 +
